<?xml version="1.0" encoding="utf-8" ?><dwsync><file name=".DS_Store" server="ftp.329521b39b0debe9.lolipop.jp" local="3489651666" remote="7787924416" Dst="-1" /><file name="isao.jpg" server="ftp.329521b39b0debe9.lolipop.jp" local="3489643276" remote="-4611698487522770308" Dst="-1" /><file name="yoake_back.png" server="ftp.329521b39b0debe9.lolipop.jp" local="3489645196" remote="7784612476" Dst="-1" /><file name="yoake_logo.png" server="ftp.329521b39b0debe9.lolipop.jp" local="3489646105" remote="-4611713262210265548" Dst="-1" /><file name="int_5.png" server="ftp.329521b39b0debe9.lolipop.jp" local="3489648731" remote="-4611698350083811436" Dst="-1" /><file name="int_1.png" server="ftp.329521b39b0debe9.lolipop.jp" local="3489648381" remote="-4611698350083811436" Dst="-1" /><file name="int_4.png" server="ftp.329521b39b0debe9.lolipop.jp" local="3489648495" remote="-4611698350083811436" Dst="-1" /><file name="int_2.png" server="ftp.329521b39b0debe9.lolipop.jp" local="3489648410" remote="7784617876" Dst="-1" /><file name="int_3.png" server="ftp.329521b39b0debe9.lolipop.jp" local="3489648455" remote="-4611698350083811436" Dst="-1" /></dwsync>